Workbook
Name \a: #N/A
Name \b: #N/A
Name \c: #REF!
Name \c: #REF!
Name \CF1: #N/A
Name \CF2: #N/A
Name \CF3: #REF!
Name \CF3: #REF!
Name \CF4: #REF!
Name \CF4: #REF!
Name \e: #REF!
Name \e: #REF!
Name \h: #N/A
Name \HL1: #N/A
Name \HL2: #N/A
Name \HL3: #REF!
Name \HL3: #REF!
Name \HL4: #REF!
Name \HL4: #REF!
Name \l: #REF!
Name \l: #REF!
Name \m: #N/A
Name \NA1: #N/A
Name \NA2: #N/A
Name \NA3: #N/A
Name \NA4: #REF!
Name \NA4: #REF!
Name \p: #N/A
Name \PL1: #N/A
Name \PL2: #N/A
Name \PL3: #N/A
Name \PL4: #REF!
Name \PL4: #REF!
Name \q: #N/A
Name \s: #N/A
Name \u: #N/A
Name \x: #N/A
Name \y: #REF!
Name \y: #REF!
Name \z: #REF!
Name \z: #REF!
Name ___tt2: #REF!
Name ___tt2: #REF!
Name ___tt3: #REF!
Name ___tt3: #REF!
Name __CBS1: #N/A
Name __DAT1: [2]Sheet1!#REF!
Name __DAT1: [2]Sheet1!#REF!
Name __DAT10: #REF!
Name __DAT10: #REF!
Name __DAT11: #REF!
Name __DAT11: #REF!
Name __DAT12: #REF!
Name __DAT12: #REF!
Name __DAT13: #REF!
Name __DAT13: #REF!
Name __DAT14: #REF!
Name __DAT14: #REF!
Name __DAT15: #REF!
Name __DAT15: #REF!

Sheet Secondary Process MC
D2: Cost Components excluded in MSU Calculation: | E2: EXCL: | F2: EXCL: | G2: EXCL: | H2: EXCL:
E3: none
B6: Machine | C6: Machine Description | D6: Process Type | E6: MSU RATE A [US$/hr] | F6: MSU RATE B [US$/hr] | G6: MSU RATE C [US$/hr] | H6: MSU RATE D [US$/hr] | I6: MSU RATE E [US$/hr] | J6: MSU RATE Z [US$ / hr] | K6: Labour [US$ / hr] | L6: Labour Head Count / Hr [Man Power] | M6: Setup [US$ / hr] | N6: Qc [US$ / hr] | O6: Setup Time (Hr)
J7: Profit Cube Rate (No depriciation) | K7: Process Labour Cost per Hour | L7: Total Labour to operate a Machine for one hour in hours | M7: SU Cost per Hour | O7: SU Time in Hours
B8: ZM1 | C8: 螺旋振磨100L | E8: =VLOOKUP($B8,'汇总FY16 BG'!$B:$L,11,0) -> 4.7001658 | F8: =VLOOKUP($B8,'汇总FY16 BG'!$B:$L,9,0) -> 2.4560749 | G8: 0 | H8: 0 | K8: 3.25 | O8: 0.37
B9: ZM2 | C9: 螺旋振磨300L | D9: Tapping | E9: =VLOOKUP($B9,'汇总FY16 BG'!$B:$L,11,0) -> 4.9765275 | F9: =VLOOKUP($B9,'汇总FY16 BG'!$B:$L,9,0) -> 2.5688746 | G9: 0 | H9: 0 | K9: 3.25 | O9: 0.37
B10: ZM3 | C10: 涡流振磨 | D10: Tapping | E10: =VLOOKUP($B10,'汇总FY16 BG'!$B:$L,11,0) -> 5.8437103 | F10: =VLOOKUP($B10,'汇总FY16 BG'!$B:$L,9,0) -> 3.1584399 | G10: 0 | H10: 0 | K10: 3.25 | O10: 0.37
B11: ZM4 | C11: 滚桶振磨 | D11: Tapping | E11: =VLOOKUP($B11,'汇总FY16 BG'!$B:$L,11,0) -> 4.6912758 | F11: =VLOOKUP($B11,'汇总FY16 BG'!$B:$L,9,0) -> 2.4771532 | G11: 0 | H11: 0 | K11: 3.25 | O11: 0.083333333
B12: SR1 | C12: 旋铆 BTO-161 | D12: TBA | E12: =VLOOKUP($B12,'汇总FY16 BG'!$B:$L,11,0) -> 3.7864157 | F12: =VLOOKUP($B12,'汇总FY16 BG'!$B:$L,9,0) -> 1.8949886 | G12: 0 | H12: 0 | K12: 3.25 | O12: 0.133
B13: SR2 | C13: 旋铆 BR1-103 | D13: TBA | E13: =VLOOKUP($B13,'汇总FY16 BG'!$B:$L,11,0) -> 3.7864153 | F13: =VLOOKUP($B13,'汇总FY16 BG'!$B:$L,9,0) -> 1.8949885 | G13: 0 | H13: 0 | K13: 3.25 | O13: 0.133
B14: CH1 | C14: 高速冷镦机 | D14: Cold Forging | E14: =VLOOKUP($B14,'汇总FY16 BG'!$B:$L,11,0) -> 15.05827 | F14: =VLOOKUP($B14,'汇总FY16 BG'!$B:$L,9,0) -> 8.2454265 | G14: 0 | H14: 0 | K14: 3.25 | O14: 0.5
B15: XS1 | C15: 吸塑成型机 | D15: Plastic Forming | E15: =VLOOKUP($B15,'汇总FY16 BG'!$B:$L,11,0) -> 16.613568 | F15: =VLOOKUP($B15,'汇总FY16 BG'!$B:$L,9,0) -> 9.4619776 | G15: 0 | H15: 0 | K15: 3.25 | O15: 3.083
B16: TM | C16: 单轴攻丝 | D16: Thunbling | E16: =VLOOKUP($B16,'汇总FY16 BG'!$B:$L,11,0) -> 3.5793415 | F16: =VLOOKUP($B16,'汇总FY16 BG'!$B:$L,9,0) -> 1.7858202 | G16: 0 | H16: 0 | K16: 3.25 | O16: 0.133
B17: TP1 | C17: 6轴攻丝 | D17: Thunbling | E17: =VLOOKUP($B17,'汇总FY16 BG'!$B:$L,11,0) -> 4.8415456 | F17: =VLOOKUP($B17,'汇总FY16 BG'!$B:$L,9,0) -> 2.3629399 | G17: 0 | H17: 0 | K17: 3.25 | O17: 0.133
B18: TP2 | C18: 10轴攻丝 | D18: Thunbling | E18: =VLOOKUP($B18,'汇总FY16 BG'!$B:$L,11,0) -> 4.498485 | F18: =VLOOKUP($B18,'汇总FY16 BG'!$B:$L,9,0) -> 2.2246559 | G18: 0 | H18: 0 | K18: 3.25 | O18: 0.133
B19: JM | C19: 砂带机 | D19: Thunbling | E19: =VLOOKUP($B19,'汇总FY16 BG'!$B:$L,11,0) -> 3.7524053 | F19: =VLOOKUP($B19,'汇总FY16 BG'!$B:$L,9,0) -> 1.8990977 | G19: 0 | H19: 0 | K19: 3.25 | O19: 0
B20: PT1 | C20: 内部电镀 | D20: Plating | E20: =VLOOKUP($B20,'汇总FY16 BG'!$B:$L,11,0) -> 857.76739 | F20: =VLOOKUP($B20,'汇总FY16 BG'!$B:$L,9,0) -> 730.86109 | G20: 0 | H20: 0 | K20: 3.25 | O20: 0.112
B21: PT2 | C21: 内部电镀 | D21: Plating | E21: =VLOOKUP($B21,'汇总FY16 BG'!$B:$L,11,0) -> 1510.5319 | F21: =VLOOKUP($B21,'汇总FY16 BG'!$B:$L,9,0) -> 1283.823 | G21: 0 | H21: 0 | K21: 3.25 | O21: 0.112
O22: 0.112
D25: Machine Cost / pc | E25: We check how many loads are required. If MOQ is lesser than the Qty / load, we will still use one full load. The full time per MOQ is calculated and the costs are divided by the MOQ
D26: Setup Cost / pc | E26: We first calculate how many setups are required for the MOQ. Number of Setups is multiplied with the Setup time and Rate and divided by MOQ
D27: Labour Cost / pc | E27: Labour cost depend on the Head count assigned to the process and the number per run. Then divided by the MOQ. No inline Packaging is assigned, only the operator. Inline packaging will be another process.
D28: Additional Cost / pc | E28: Fix items that are not in the MSU can be added inside additional costs. E.g. special tooling like expensive drills that need to be replaced after producing a certain amount
D29: Quality Cost / pc | E29: Quality work with the time required for quality. This inspection needs to be done when each run starts.

Sheet Stamping Process MC
D2: Cost Components excluded in MSU Calculation: | E2: EXCL: | F2: EXCL: | G2: EXCL: | H2: EXCL:
E3: none
B6: Machine | C6: Machine Description | D6: Process Type | E6: MSU RATE A [US$/hr] | F6: MSU RATE B [US$/hr] | G6: MSU RATE C [US$/hr] | H6: MSU RATE D [US$/hr] | I6: MSU RATE E [US$/hr] | J6: MSU RATE Z [US$ / hr] | K6: Labour [US$ / hr] | L6: Labour Head Count / Hr [Man Power] | M6: Setup [US$ / hr] | N6: Setup Time (hr) | O6: Labour Operation (LO) | P6: Labour Packaging (LP) | Q6: Labour Quality (LQ) | R6: DIR. LABOR-STAMP | S6: DIR. LABOR-PACKING | T6: QA / LOAD-STAMP
J7: Profit Cube Rate (No depriciation) | K7: Process Labour Cost per Hour | L7: Total Labour to operate a Machine for one hour in hours | M7: SU Cost per Hour | N7: SU Time in Hours
B8: A200T1 | C8: P200T 工作中心（小台面） | D8: Progressive | E8: =VLOOKUP($B8,'汇总FY16 BG'!$B:$L,11,0) -> 22.0878 | F8: =VLOOKUP($B8,'汇总FY16 BG'!$B:$L,9,0) -> 10.275173 | G8: 0 | H8: 0 | K8: 3.25 | O8: 0.60240964 | Q8: 0.39759036 | R8: 3.24 | S8: 2.97 | T8: 4.28
B9: A200T2 | C9: P200T 工作中心（大台面） | D9: Progressive | E9: =VLOOKUP($B9,'汇总FY16 BG'!$B:$L,11,0) -> 28.46526 | F9: =VLOOKUP($B9,'汇总FY16 BG'!$B:$L,9,0) -> 15.044484 | G9: 0 | H9: 0 | K9: 3.25 | O9: 0.60240964 | Q9: 0.39759036
B10: A300T | C10: P300T 工作中心 | D10: Progressive | E10: =VLOOKUP($B10,'汇总FY16 BG'!$B:$L,11,0) -> 34.420248 | F10: =VLOOKUP($B10,'汇总FY16 BG'!$B:$L,9,0) -> 17.813699 | G10: 0 | H10: 0 | K10: 3.25 | O10: 0.60240964 | Q10: 0.39759036
B11: A500T | C11: P500T 工作中心 | D11: Progressive | E11: =VLOOKUP($B11,'汇总FY16 BG'!$B:$L,11,0) -> 47.76699 | F11: =VLOOKUP($B11,'汇总FY16 BG'!$B:$L,9,0) -> 27.111419 | G11: 0 | H11: 0 | K11: 3.25 | O11: 0.7518797 | Q11: 0.2481203
B12: M160T | C12: M160T 工作中心(单动) | D12: Manual | E12: =VLOOKUP($B12,'汇总FY16 BG'!$B:$L,11,0) -> 10.442206 | F12: =VLOOKUP($B12,'汇总FY16 BG'!$B:$L,9,0) -> 5.7218662 | G12: 0 | H12: 0 | K12: 3.25 | O12: 0.7518797 | Q12: 0.2481203
B13: S110T | C13: 110T高速冲压 | D13: Progressive | E13: =VLOOKUP($B13,'汇总FY16 BG'!$B:$L,11,0) -> 10.870784 | F13: =VLOOKUP($B13,'汇总FY16 BG'!$B:$L,9,0) -> 6.5663635 | G13: 0 | H13: 0 | K13: 3.25 | O13: 0.60240964 | Q13: 0.39759036
B14: S60T | C14: 60T高速冲压 | D14: Progressive | E14: =VLOOKUP($B14,'汇总FY16 BG'!$B:$L,11,0) -> 9.9238798 | F14: =VLOOKUP($B14,'汇总FY16 BG'!$B:$L,9,0) -> 5.8340367 | G14: 0 | H14: 0 | K14: 3.25 | O14: 0.60240964 | Q14: 0.39759036
B15: C75300T | C15: TNX-300T冲床 （Haier） | D15: Progressive | E15: =VLOOKUP($B15,'汇总FY16 BG'!$B:$L,11,0) -> 22.967062 | F15: =VLOOKUP($B15,'汇总FY16 BG'!$B:$L,9,0) -> 13.267657 | G15: 0 | H15: 0 | K15: 3.25 | O15: 0.5 | Q15: 0.5
B16: C75400T | C16: TNX-400T冲床 （Haier） | D16: Progressive | E16: =VLOOKUP($B16,'汇总FY16 BG'!$B:$L,11,0) -> 24.673964 | F16: =VLOOKUP($B16,'汇总FY16 BG'!$B:$L,9,0) -> 14.198803 | G16: 0 | H16: 0 | K16: 3.25 | O16: 0.5 | Q16: 0.5
D25: Machine Cost / pc | E25: Qty per Hr first calculate with 3600 divided by Cycle Time. If there is Effiency and cavity , Qty per Hr is mutipled with cavity and effiency%. Machine Cost/Pc is calculated MSU Rate divided by Qty per Hr.
D26: Setup Cost / pc | E26: We first calculate how many setups are required for the MOQ. Number of Setups is multiplied with the Setup time and Rate and divided by MOQ
D27: Labour Cost / pc | E27: Labour cost depend on the Head count assigned to the process and the number per run. Then divided by the MOQ. No inline Packaging is assigned, only the operator. Inline packaging will be another process.

Sheet SoftTool Process MC
B2: Machine | C2: Machine Description | D2: Process Type | E2: MSU RATE A [US$/hr] | F2: MSU RATE B [US$/hr] | G2: MSU RATE C [US$/hr] | H2: MSU RATE D [US$/hr] | I2: MSU RATE E [US$/hr] | J2: MSU RATE Z [US$ / hr] | K2: Labour [US$ / hr] | L2: Labour Head Count / Hr [Man Power] | M2: Setup [US$ / hr] | N2: Setup Time (hr) | O2: Capacity [SPM,Surface Area] | P2: Process Rate per Capacity
J3: Profit Cube Rate (No depriciation) | K3: Process Labour Cost per Hour | L3: Total Labour to operate a Machine for one hour in hours | M3: SU Cost per Hour | N3: SU Time in Hours | P3: Cost/Stroke or Mins or SurfaceArea
D21: Machine Cost / pc | E21: Qty per Hr first calculate with Strokes Per Minute is multipled with 60. Machine Cost/Pc is calculated MSU Rate divided by Qty per Hr.
D22: Setup Cost / pc | E22: We first calculate how many setups are required for the MOQ. Number of Setups is multiplied with the Setup time and Rate and divided by MOQ
D23: Labour Cost / pc | E23: Labour cost depend on the Head count assigned to the process and the number per run. Then divided by the MOQ. No inline Packaging is assigned, only the operator. Inline packaging will be another process.

Sheet ColdForging Process MC
B2: Machine | C2: Machine Description | D2: Process Type | E2: MSU RATE A [US$/hr] | F2: MSU RATE B [US$/hr] | G2: MSU RATE C [US$/hr] | H2: MSU RATE D [US$/hr] | I2: MSU RATE E [US$/hr] | J2: MSU RATE Z [US$ / hr] | K2: Labour [US$ / hr] | L2: Labour Head Count / Hr [Man Power] | M2: Setup [US$ / hr] | N2: Setup Time (hr)
J3: Profit Cube Rate (No depriciation) | K3: Process Labour Cost per Hour | L3: Total Labour to operate a Machine for one hour in hours | M3: SU Cost per Hour | N3: SU Time in Hours
D21: Machine Cost / pc | E21: Qty per Hr first calculate with 3600 divided by Cycle Time. If there is Effiency and cavity , Qty per Hr is mutipled with cavity and effiency%. Machine Cost/Pc is calculated MSU Rate divided by Qty per Hr.
D22: Setup Cost / pc | E22: We first calculate how many setups are required for the MOQ. Number of Setups is multiplied with the Setup time and Rate and divided by MOQ
D23: Labour Cost / pc | E23: Labour cost depend on the Head count assigned to the process and the number per run. Then divided by the MOQ. No inline Packaging is assigned, only the operator. Inline packaging will be another process.

Sheet DieCasting Process MC
B2: Machine | C2: Machine Description | D2: Process Type | E2: MSU RATE A [US$/hr] | F2: MSU RATE B [US$/hr] | G2: MSU RATE C [US$/hr] | H2: MSU RATE D [US$/hr] | I2: MSU RATE E [US$/hr] | J2: MSU RATE Z [US$ / hr] | K2: Labour [US$ / hr] | L2: Labour Head Count / Hr [Man Power] | M2: Setup [US$ / hr] | N2: Setup Time (hr)
J3: Profit Cube Rate (No depriciation) | K3: Process Labour Cost per Hour | L3: Total Labour to operate a Machine for one hour in hours | M3: SU Cost per Hour | N3: SU Time in Hours
D21: Machine Cost / pc | E21: Qty per Hr first calculate with 3600 divided by Cycle Time. If there is Effiency and cavity , Qty per Hr is mutipled with cavity and effiency%. Machine Cost/Pc is calculated MSU Rate divided by Qty per Hr.
D22: Setup Cost / pc | E22: We first calculate how many setups are required for the MOQ. Number of Setups is multiplied with the Setup time and Rate and divided by MOQ
D23: Labour Cost / pc | E23: Labour cost depend on the Head count assigned to the process and the number per run. Then divided by the MOQ. No inline Packaging is assigned, only the operator. Inline packaging will be another process.

Sheet Factory Labour and MasterData
C1: US$
A2: selfEvaporatingOilFinishingRate [US$] | B2: Self Evaporating Oil Finshing Rate | C2: 0.0025
A3: degreasingFinishingRate [US$] | B3: Degreasing Finishing Rate | C3: 0.005
A4: labourCostAssembly [US$] | B4: Labour Cost (Assembly) for Assembly Process | C4: 3.25
A5: labourCostEngineering [US$] | B5: Labour Cost (Engineering) | C5: 3.25
A6: labourCostFloorArea [US$] | B6: Floor Area Cost per sq meter | C6: 3.25
A7: labourCostPackaging [US$] | B7: Labour Cost (Packaging) | C7: 3.25
A10: New Investment | B10: New Investment
A12: factoryElectricalPower [US$] | B12: Electrical Cost / kwh
A13: factoryWaterCuM [US$] | B13: Water/ Coolant Rate per Cu.m
A14: factoryAllowancePercent [%] | B14: Allowance Percent for Direct Labour ( the data is needed to calculate Allowance / Month)
A15: factoryEmpContrPercent [%] | B15: Emp Contr Percent for Direct Labour (the data is needed to calculate Emp Contr/Month)
A17: mcOperatorBasicSalaryPerMth [US$] | B17: M/C Operators Basic Salary Per Month
A18: packerBasicSalaryPerMth [US$] | B18: Packer Basic Salary Per Month
A19: materialHandlerBasicSalaryPerMth [US$] | B19: Material Handler Basic Salary Per Month
A20: qcInspectorBasicSalaryPerMth [US$] | B20: QC Inspector Basic Salary Per Month
A21: clerkBasicSalaryPerMth [US$] | B21: Clerk Basic Salary Per Month
A22: storeKeeperBasicSalaryPerMth [US$] | B22: Store Keeper Basic Salary Per Month
A23: driverBasicSalaryPerMth [US$] | B23: Driver Basic Salary Per Month
... A28: processEngineerBasicSalaryPerMth [US$] | B28: Process Engineer Basic Salary Per Month

Sheet Sheet1
A1: ------------------- | B1: ----------------------------- | C1: ---------------------
A2: workstation | B2: MSU | C2: cost
A3: ------------------- | B3: ----------------------------- | C3: ---------------------
A4: pci:WS_A200T1 | B4: pcs-kb:WS_A200T1_COST_A | C4: 22
A5: pci:WS_A200T1 | B5: pcs-kb:WS_A200T1_COST_B | C5: 10.28
A6: pci:WS_A200T1 | B6: pcs-kb:WS_A200T1_COST_C | C6: 0
A7: pci:WS_A200T1 | B7: pcs-kb:WS_A200T1_COST_D | C7: 0
A8: pci:WS_A200T2 | B8: pcs-kb:WS_A200T2_COST_A | C8: 22
A9: pci:WS_A200T2 | B9: pcs-kb:WS_A200T2_COST_B | C9: 15.04
A10: pci:WS_A200T2 | B10: pcs-kb:WS_A200T2_COST_C | C10: 0
A11: pci:WS_A200T2 | B11: pcs-kb:WS_A200T2_COST_D | C11: 0
A12: pci:WS_A300T_HITL | B12: pcs-kb:WS_A300T_HITL_COST_A | C12: 28
A13: pci:WS_A300T_HITL | B13: pcs-kb:WS_A300T_HITL_COST_B | C13: 17.81
A14: pci:WS_A300T_HITL | B14: pcs-kb:WS_A300T_HITL_COST_C | C14: 0
A15: pci:WS_A300T_HITL | B15: pcs-kb:WS_A300T_HITL_COST_D | C15: 0
... A39: pci:WS_S60T | B39: pcs-kb:WS_S60T_COST_D | C39: 0

Sheet Sheet2
A1: ------------- | B1: --------------------- | C1: ---------------------
A2: workstation | B2: MSU | C2: cost
A3: pci:WS_CH1 | B3: pcs-kb:WS_CH1_COST_A | C3: 9999
A4: pci:WS_CH1 | B4: pcs-kb:WS_CH1_COST_B | C4: 8.25
A5: pci:WS_CH1 | B5: pcs-kb:WS_CH1_COST_C | C5: 0
A6: pci:WS_CH1 | B6: pcs-kb:WS_CH1_COST_D | C6: 0
A7: pci:WS_JM | B7: pcs-kb:WS_JM_COST_A | C7: 1.97
A8: pci:WS_JM | B8: pcs-kb:WS_JM_COST_B | C8: 1.9
A9: pci:WS_JM | B9: pcs-kb:WS_JM_COST_C | C9: 0
A10: pci:WS_JM | B10: pcs-kb:WS_JM_COST_D | C10: 0
A11: pci:WS_PT1 | B11: pcs-kb:WS_PT1_COST_A | C11: 857.77
A12: pci:WS_PT1 | B12: pcs-kb:WS_PT1_COST_B | C12: 730.86
A13: pci:WS_PT1 | B13: pcs-kb:WS_PT1_COST_C | C13: 0
A14: pci:WS_PT1 | B14: pcs-kb:WS_PT1_COST_D | C14: 0
... A58: pci:WS_ZM4 | B58: pcs-kb:WS_ZM4_COST_D | C58: 0

Sheet Reference-->

Sheet FY16 BG Labor hour
A1: Cost Center | B1: ActTyp | C1: Act. type short text | D1: Act. type short text | E1: 备注 | F1: FY16 Budget
A2: 3031P3200 | B2: C4A001 | C2: Production | D2: ADJ. TOOL-STAMP 调模 | E2: 模具直接人员 | F2: 4.4408438
A3: 3031P3105 | B3: C4A101 | C3: HATL Haier Project | D3: ADJ. TOOL-STAMP 调模 | E3: 模具直接人员 | F3: 4.4408438
A4: 3031M1200 | B4: C4A002 | C4: Prod Plastic Molding | D4: ADJ. TOOL-PLASTIC | E4: 吸塑人员 | F4: 6.6302179
A5: 3031P3200 | B5: C4L001 | C5: Production | D5: DIR. LABOR-STAMP人工 | E5: 冲压直接人员 | F5: 3.2439579
A6: 3031P3105 | B6: C4L101 | C6: HATL Haier Project | D6: DIR. LABOR-STAMP人工 | E6: 冲压直接人员 | F6: 3.2439579 | H6: Average
A7: 3031P3201 | B7: C4L002 | C7: Plating & Cleaning | D7: DIRLABOR-PLATING人工 | E7: 表面处理部直接人员 | F7: 3.5152453 | H7: =AVERAGE(F5:F11) -> 3.2510692
A8: 3031P3200 | B8: C4L003 | C8: Production | D8: DIR. LABOR-TAPPING人 | E8: 攻丝、振磨直接人员 | F8: 3.2635085
A9: 3031P3200 | B9: C4L005 | C9: Production | D9: DIR. LABOR-ASSEMBLY | E9: 组装（ 攻丝直接人员） | F9: 3.2635085
A10: 3031P3200 | B10: C4L004 | C10: Production | D10: DIR. LABOR-PACKING人 | E10: 包装直接人员 | F10: 2.9753213
A11: 3031M1200 | B11: C4L006 | C11: Prod Plastic Molding | D11: DIR. LABOR-PLASTIC | E11: 吸塑直接人员 | F11: 3.2519849
A12: 3031M1200 | B12: C4Q001 | C12: Prod Plastic Molding | D12: QA / LOAD-STAMP 检查 | E12: 品管部直接人员 | F12: 4.278507
A13: 3031P3200 | B13: C4Q001 | C13: Production | D13: QA / LOAD-STAMP 检查 | E13: 品管部直接人员 | F13: 4.278507
A14: 3031P3201 | B14: C4Q002 | C14: Plating & Cleaning | D14: QA / LOAD-PLANT 检查 | E14: 品管部直接人员 | F14: 4.278507
A15: 3031P3105 | B15: C4Q101 | C15: HATL Haier Project | D15: QA / LOAD-STAMP 检查 | E15: 品管部直接人员 | F15: 4.278507
A16: 3031P3200 | B16: C4S001 | C16: Production | D16: SETUP TIME-STAMP上模 | E16: 模具直接人员 | F16: 4.4408438
A17: 3031P3201 | B17: C4S002 | C17: Plating & Cleaning | D17: SETUP TIME-PLANT上模 | E17: 表面处理部直接人员 | F17: 3.5152453
A18: 3031P3105 | B18: C4S101 | C18: HATL Haier Project | D18: SETUP TIME-STAMP上模 | E18: 模具人员直接人员 | F18: 4.4408438
A19: 3031M1200 | B19: C4S003 | C19: Prod Plastic Molding | D19: SETUP TIME-PLASTIC | E19: 吸塑人员 | F19: 6.6302179

Sheet 汇总FY16 BG
J1: 15.06.08 Activity rate
B2: Work center | C2: Cost center | D2: ActTyp | E2: Description | F2: Shift | H2: Machine direct hour | J2: Machine cost per hour | L2: Total Marketing cost
H3: ( USD/H ) | J3: ( USD/H ) | L3: ( USD/H )
A5: 1 | B5: A200T1 | C5: 3031P3200 | D5: C4M002 | E5: P200T 工作中心（小台面） | F5: =VLOOKUP($B5,'[1]Stamping - 3 shift'!$C:$AR,16,FALSE) -> 3 | H5: =VLOOKUP($B5,'[1]Stamping - 3 shift'!$C:$AR,35,FALSE) -> 0.91692102 | J5: =VLOOKUP($B5,'[1]Stamping - 3 shift'!$C:$AR,37,FALSE) -> 10.275173 | L5: =VLOOKUP($B5,'[1]Stamping - 3 shift'!$C:$AR,39,FALSE) -> 22.0878
A6: 2 | B6: A200T2 | C6: 3031P3200 | D6: C4M003 | E6: P200T 工作中心（大台面） | F6: =VLOOKUP($B6,'[1]Stamping - 3 shift'!$C:$AR,16,FALSE) -> 3 | H6: =VLOOKUP($B6,'[1]Stamping - 3 shift'!$C:$AR,35,FALSE) -> 4.70141 | J6: =VLOOKUP($B6,'[1]Stamping - 3 shift'!$C:$AR,37,FALSE) -> 15.044484 | L6: =VLOOKUP($B6,'[1]Stamping - 3 shift'!$C:$AR,39,FALSE) -> 28.46526
A7: 3 | B7: A300T | C7: 3031P3200 | D7: C4M004 | E7: P300T 工作中心 | F7: =VLOOKUP($B7,'[1]Stamping - 3 shift'!$C:$AR,16,FALSE) -> 3 | H7: =VLOOKUP($B7,'[1]Stamping - 3 shift'!$C:$AR,35,FALSE) -> 5.3361877 | J7: =VLOOKUP($B7,'[1]Stamping - 3 shift'!$C:$AR,37,FALSE) -> 17.813699 | L7: =VLOOKUP($B7,'[1]Stamping - 3 shift'!$C:$AR,39,FALSE) -> 34.420248
A8: 4 | B8: A500T | C8: 3031P3200 | D8: C4M023 | E8: P500T 工作中心 | F8: =VLOOKUP($B8,'[1]Stamping - 3 shift'!$C:$AR,16,FALSE) -> 3 | H8: =VLOOKUP($B8,'[1]Stamping - 3 shift'!$C:$AR,35,FALSE) -> 12.838695 | J8: =VLOOKUP($B8,'[1]Stamping - 3 shift'!$C:$AR,37,FALSE) -> 27.111419 | L8: =VLOOKUP($B8,'[1]Stamping - 3 shift'!$C:$AR,39,FALSE) -> 47.76699
A9: 5 | B9: M160T | C9: 3031P3200 | D9: C4M001 | E9: M160T 工作中心(单动) | F9: =VLOOKUP($B9,'[1]Stamping - 3 shift'!$C:$AR,16,FALSE) -> 3 | H9: =VLOOKUP($B9,'[1]Stamping - 3 shift'!$C:$AR,35,FALSE) -> 1.5222362 | J9: =VLOOKUP($B9,'[1]Stamping - 3 shift'!$C:$AR,37,FALSE) -> 5.7218662 | L9: =VLOOKUP($B9,'[1]Stamping - 3 shift'!$C:$AR,39,FALSE) -> 10.442206
A10: 6 | B10: S110T | C10: 3031P3200 | D10: C4M006 | E10: 110T高速冲压 | F10: =VLOOKUP($B10,'[1]Stamping - 3 shift'!$C:$AR,16,FALSE) -> 3 | H10: =VLOOKUP($B10,'[1]Stamping - 3 shift'!$C:$AR,35,FALSE) -> 2.9327338 | J10: =VLOOKUP($B10,'[1]Stamping - 3 shift'!$C:$AR,37,FALSE) -> 6.5663635 | L10: =VLOOKUP($B10,'[1]Stamping - 3 shift'!$C:$AR,39,FALSE) -> 10.870784
A11: 7 | B11: S60T | C11: 3031P3200 | D11: C4M005 | E11: 60T高速冲压 | F11: =VLOOKUP($B11,'[1]Stamping - 3 shift'!$C:$AR,16,FALSE) -> 3 | H11: =VLOOKUP($B11,'[1]Stamping - 3 shift'!$C:$AR,35,FALSE) -> 2.1916877 | J11: =VLOOKUP($B11,'[1]Stamping - 3 shift'!$C:$AR,37,FALSE) -> 5.8340367 | L11: =VLOOKUP($B11,'[1]Stamping - 3 shift'!$C:$AR,39,FALSE) -> 9.9238798
A12: 8 | B12: C75300T | C12: 3031P3105 | D12: C4M101 | E12: TNX-300T冲床 （Haier） | F12: =VLOOKUP($B12,'[1]Stamping - 3 shift'!$C:$AR,16,FALSE) -> 3 | H12: =VLOOKUP($B12,'[1]Stamping - 3 shift'!$C:$AR,35,FALSE) -> 5.3919284 | J12: =VLOOKUP($B12,'[1]Stamping - 3 shift'!$C:$AR,37,FALSE) -> 13.267657 | L12: =VLOOKUP($B12,'[1]Stamping - 3 shift'!$C:$AR,39,FALSE) -> 22.967062
A13: 9 | B13: C75400T | C13: 3031P3105 | D13: C4M102 | E13: TNX-400T冲床 （Haier） | F13: =VLOOKUP($B13,'[1]Stamping - 3 shift'!$C:$AR,16,FALSE) -> 3 | H13: =VLOOKUP($B13,'[1]Stamping - 3 shift'!$C:$AR,35,FALSE) -> 5.9213734 | J13: =VLOOKUP($B13,'[1]Stamping - 3 shift'!$C:$AR,37,FALSE) -> 14.198803 | L13: =VLOOKUP($B13,'[1]Stamping - 3 shift'!$C:$AR,39,FALSE) -> 24.673964
A14: 10 | B14: ZM1 | C14: 3031P3200 | D14: C4M007 | E14: 螺旋振磨100L | F14: =VLOOKUP($B14,'[1]Stamping - 3 shift'!$C:$AR,16,FALSE) -> 3 | H14: =VLOOKUP($B14,'[1]Stamping - 3 shift'!$C:$AR,35,FALSE) -> 0.21428979 | J14: =VLOOKUP($B14,'[1]Stamping - 3 shift'!$C:$AR,37,FALSE) -> 2.4560749 | L14: =VLOOKUP($B14,'[1]Stamping - 3 shift'!$C:$AR,39,FALSE) -> 4.7001658
A15: 11 | B15: ZM2 | C15: 3031P3200 | D15: C4M008 | E15: 螺旋振磨300L | F15: =VLOOKUP($B15,'[1]Stamping - 3 shift'!$C:$AR,16,FALSE) -> 3 | H15: =VLOOKUP($B15,'[1]Stamping - 3 shift'!$C:$AR,35,FALSE) -> 0.20342543 | J15: =VLOOKUP($B15,'[1]Stamping - 3 shift'!$C:$AR,37,FALSE) -> 2.5688746 | L15: =VLOOKUP($B15,'[1]Stamping - 3 shift'!$C:$AR,39,FALSE) -> 4.9765275
A16: 12 | B16: ZM3 | C16: 3031P3200 | D16: C4M009 | E16: 涡流振磨 | F16: =VLOOKUP($B16,'[1]Stamping - 3 shift'!$C:$AR,16,FALSE) -> 3 | H16: =VLOOKUP($B16,'[1]Stamping - 3 shift'!$C:$AR,35,FALSE) -> 0.65052907 | J16: =VLOOKUP($B16,'[1]Stamping - 3 shift'!$C:$AR,37,FALSE) -> 3.1584399 | L16: =VLOOKUP($B16,'[1]Stamping - 3 shift'!$C:$AR,39,FALSE) -> 5.8437103
... A25: 21 | B25: JM | C25: 3031P3200 | D25: C4M018 | E25: 砂带机 | F25: =VLOOKUP($B25,'[1]Stamping - 3 shift'!$C:$AR,16,FALSE) -> 3 | H25: =VLOOKUP($B25,'[1]Stamping - 3 shift'!$C:$AR,35,FALSE) -> 0.03020185 | J25: =VLOOKUP($B25,'[1]Stamping - 3 shift'!$C:$AR,37,FALSE) -> 1.8990977 | L25: =VLOOKUP($B25,'[1]Stamping - 3 shift'!$C:$AR,39,FALSE) -> 3.7524053
A27: 22 | B27: PT1 | C27: 3031P3201 | D27: C4M019 | E27: 内部电镀 | F27: =VLOOKUP($B27,'[1]Plating - 3 shift'!$C:$AO,16,FALSE) -> 3 | H27: =VLOOKUP($B27,'[1]Plating - 3 shift'!$C:$AO,35,FALSE) -> 21.279371 | J27: =VLOOKUP($B27,'[1]Plating - 3 shift'!$C:$AO,37,FALSE) -> 730.86109 | L27: =VLOOKUP($B27,'[1]Plating - 3 shift'!$C:$AO,39,FALSE) -> 857.76739
A28: 23 | B28: PT2 | C28: 3031P3201 | D28: C4M020 | E28: 内部电镀 | F28: =VLOOKUP($B28,'[1]Plating - 3 shift'!$C:$AO,16,FALSE) -> 3 | H28: =VLOOKUP($B28,'[1]Plating - 3 shift'!$C:$AO,35,FALSE) -> 90.218344 | J28: =VLOOKUP($B28,'[1]Plating - 3 shift'!$C:$AO,37,FALSE) -> 1283.823 | L28: =VLOOKUP($B28,'[1]Plating - 3 shift'!$C:$AO,39,FALSE) -> 1510.5319
